SDD/__init__.py
SDD/data/__init__.py
SDD/debug/__init__.py
SDD/outputs/__init__.py
SDD/utils/DatasetGenerator.py
SDD/utils/Detector.py
SDD/utils/GreedyRepulsion.py
SDD/utils/LstGenerator.py
SDD/utils/Models.py
SDD/utils/Run.py
SDD/utils/Train_Models.py
SDD/utils/Video2images.py
SDD/utils/VideoRead.py
SDD/utils/View_Transformer.py
SDD/utils/__init__.py
SDD/utils/distance_label.py
SDD/utils/generate_top.py
SDD/utils/ssd_train.py
SDD/utils/yolo_train.py
SDD-0.2.2.7.dist-info/LICENSE
SDD-0.2.2.7.dist-info/METADATA
SDD-0.2.2.7.dist-info/WHEEL
SDD-0.2.2.7.dist-info/top_level.txt
SDD-0.2.2.7.dist-info/zip-safe
SDD-0.2.2.7.dist-info/RECORD
